[
  {
    "word": "Benny",
    "start": 0.0,
    "end": 0.26
  },
  {
    "word": "called",
    "start": 0.26,
    "end": 0.54
  },
  {
    "word": "his",
    "start": 0.54,
    "end": 0.76
  },
  {
    "word": "best",
    "start": 0.76,
    "end": 0.94
  },
  {
    "word": "friend",
    "start": 0.94,
    "end": 1.2
  },
  {
    "word": "Zara",
    "start": 1.2,
    "end": 1.52
  },
  {
    "word": "on",
    "start": 1.52,
    "end": 1.8
  },
  {
    "word": "Daddy's",
    "start": 1.8,
    "end": 2.2
  },
  {
    "word": "phone.",
    "start": 2.2,
    "end": 2.4
  },
  {
    "word": "Zara,",
    "start": 3.34,
    "end": 3.76
  },
  {
    "word": "I",
    "start": 4.16,
    "end": 4.44
  },
  {
    "word": "am",
    "start": 4.44,
    "end": 4.54
  },
  {
    "word": "making",
    "start": 4.54,
    "end": 4.8
  },
  {
    "word": "pancakes.",
    "start": 4.8,
    "end": 5.3
  },
  {
    "word": "You",
    "start": 5.98,
    "end": 6.3
  },
  {
    "word": "have",
    "start": 6.3,
    "end": 6.46
  },
  {
    "word": "to",
    "start": 6.46,
    "end": 6.6
  },
  {
    "word": "come",
    "start": 6.6,
    "end": 6.78
  },
  {
    "word": "over",
    "start": 6.78,
    "end": 6.98
  },
  {
    "word": "right",
    "start": 6.98,
    "end": 7.3
  },
  {
    "word": "now.\"",
    "start": 7.3,
    "end": 8.74
  },
  {
    "word": "Zara",
    "start": 8.74,
    "end": 9.14
  },
  {
    "word": "lived",
    "start": 9.14,
    "end": 9.38
  },
  {
    "word": "just",
    "start": 9.38,
    "end": 9.64
  },
  {
    "word": "next",
    "start": 9.64,
    "end": 9.88
  },
  {
    "word": "door.",
    "start": 9.88,
    "end": 10.18
  },
  {
    "word": "She",
    "start": 10.78,
    "end": 10.98
  },
  {
    "word": "arrived",
    "start": 10.98,
    "end": 11.3
  },
  {
    "word": "in",
    "start": 11.3,
    "end": 11.5
  },
  {
    "word": "four",
    "start": 11.5,
    "end": 11.74
  },
  {
    "word": "minutes.",
    "start": 11.74,
    "end": 12.04
  },
  {
    "word": "She",
    "start": 12.7,
    "end": 12.92
  },
  {
    "word": "was",
    "start": 12.92,
    "end": 13.04
  },
  {
    "word": "still",
    "start": 13.04,
    "end": 13.32
  },
  {
    "word": "wearing",
    "start": 13.32,
    "end": 13.6
  },
  {
    "word": "her",
    "start": 13.6,
    "end": 13.82
  },
  {
    "word": "pajamas",
    "start": 13.82,
    "end": 14.26
  },
  {
    "word": "with",
    "start": 14.26,
    "end": 14.72
  },
  {
    "word": "the",
    "start": 14.72,
    "end": 14.88
  },
  {
    "word": "little",
    "start": 14.88,
    "end": 15.08
  },
  {
    "word": "tigers",
    "start": 15.08,
    "end": 15.38
  },
  {
    "word": "on",
    "start": 15.38,
    "end": 15.68
  },
  {
    "word": "them.",
    "start": 15.68,
    "end": 15.86
  },
  {
    "word": "I",
    "start": 16.42,
    "end": 16.7
  },
  {
    "word": "brought",
    "start": 16.7,
    "end": 16.94
  },
  {
    "word": "my",
    "start": 16.94,
    "end": 17.22
  },
  {
    "word": "apron.",
    "start": 17.22,
    "end": 17.6
  },
  {
    "word": "She",
    "start": 18.14,
    "end": 18.32
  },
  {
    "word": "announced",
    "start": 18.32,
    "end": 18.7
  },
  {
    "word": "proudly.",
    "start": 18.7,
    "end": 19.18
  },
  {
    "word": "Perfect.",
    "start": 19.98,
    "end": 20.32
  },
  {
    "word": "Said",
    "start": 21.0,
    "end": 21.2
  },
  {
    "word": "Benny.",
    "start": 21.2,
    "end": 21.48
  },
  {
    "word": "You",
    "start": 22.14,
    "end": 22.28
  },
  {
    "word": "are",
    "start": 22.28,
    "end": 22.46
  },
  {
    "word": "in",
    "start": 22.46,
    "end": 22.56
  },
  {
    "word": "charge",
    "start": 22.56,
    "end": 22.8
  },
  {
    "word": "of",
    "start": 22.8,
    "end": 23.02
  },
  {
    "word": "the",
    "start": 23.02,
    "end": 23.14
  },
  {
    "word": "bowl.",
    "start": 23.14,
    "end": 23.38
  }
]